universal_transfer_operator/__init__.py
universal_transfer_operator/constants.py
universal_transfer_operator/exceptions.py
universal_transfer_operator/settings.py
universal_transfer_operator/universal_transfer_operator.py
universal_transfer_operator/utils.py
universal_transfer_operator/data_providers/__init__.py
universal_transfer_operator/data_providers/base.py
universal_transfer_operator/data_providers/database/__init__.py
universal_transfer_operator/data_providers/database/base.py
universal_transfer_operator/data_providers/database/snowflake.py
universal_transfer_operator/data_providers/database/sqlite.py
universal_transfer_operator/data_providers/database/google/__init__.py
universal_transfer_operator/data_providers/database/google/bigquery.py
universal_transfer_operator/data_providers/dataframe/Pandasdataframe.py
universal_transfer_operator/data_providers/dataframe/base.py
universal_transfer_operator/data_providers/filesystem/__init__.py
universal_transfer_operator/data_providers/filesystem/base.py
universal_transfer_operator/data_providers/filesystem/local.py
universal_transfer_operator/data_providers/filesystem/sftp.py
universal_transfer_operator/data_providers/filesystem/aws/__init__.py
universal_transfer_operator/data_providers/filesystem/aws/s3.py
universal_transfer_operator/data_providers/filesystem/google/__init__.py
universal_transfer_operator/data_providers/filesystem/google/cloud/__init__.py
universal_transfer_operator/data_providers/filesystem/google/cloud/gcs.py
universal_transfer_operator/datasets/__init__.py
universal_transfer_operator/datasets/apis.py
universal_transfer_operator/datasets/base.py
universal_transfer_operator/datasets/table.py
universal_transfer_operator/datasets/dataframe/__init__.py
universal_transfer_operator/datasets/dataframe/base.py
universal_transfer_operator/datasets/file/__init__.py
universal_transfer_operator/datasets/file/base.py
universal_transfer_operator/datasets/file/types/__init__.py
apache_airflow_provider_transfers-0.1.2.dist-info/entry_points.txt
apache_airflow_provider_transfers-0.1.2.dist-info/licenses/LICENSE
apache_airflow_provider_transfers-0.1.2.dist-info/WHEEL
apache_airflow_provider_transfers-0.1.2.dist-info/METADATA
apache_airflow_provider_transfers-0.1.2.dist-info/RECORD
