Metadata-Version: 2.4
Name: apache-airflow-provider-transfers
Version: 0.1.2
Summary: This project provides the Universal Transfer Operator to seamlessly transfer data from source to destination Datasets via a single operator invocation within DAGs.
Keywords: airflow,provider,astronomer,sql,decorator,task flow,elt,etl,dag
Author-email: Astronomer <humans@astronomer.io>
Requires-Python: >=3.7
Classifier: Development Status :: 7 - Inactive
Classifier: License :: OSI Approved :: Apache Software License
Classifier: Topic :: Database
Classifier: Framework :: Apache Airflow
Classifier: Programming Language :: Python :: 3
Classifier: Programming Language :: Python :: 3 :: Only
Classifier: Programming Language :: Python :: 3.7
Classifier: Programming Language :: Python :: 3.8
Classifier: Programming Language :: Python :: 3.9
License-File: LICENSE
Requires-Dist: apache-airflow>=2.0
Requires-Dist: attrs>=20.0
Requires-Dist: pandas>=1.3.4,<2.0.0
Requires-Dist: pyarrow
Requires-Dist: python-frontmatter
Requires-Dist: smart-open
Requires-Dist: SQLAlchemy>=1.3.18
Requires-Dist: apache-airflow-providers-common-sql
Requires-Dist: apache-airflow-providers-amazon ; extra == "all"
Requires-Dist: apache-airflow-providers-google>=6.4.0 ; extra == "all"
Requires-Dist: apache-airflow-providers-snowflake ; extra == "all"
Requires-Dist: smart-open[all]>=5.2.1 ; extra == "all"
Requires-Dist: snowflake-connector-python[pandas]<3.0.0 ; extra == "all"
Requires-Dist: snowflake-sqlalchemy>=1.2.0 ; extra == "all"
Requires-Dist: sqlalchemy-bigquery>=1.3.0 ; extra == "all"
Requires-Dist: s3fs ; extra == "all"
Requires-Dist: protobuf<=3.20 ; extra == "all"
Requires-Dist: openlineage-airflow>=0.17.0 ; extra == "all"
Requires-Dist: airflow-provider-fivetran>=1.1.3 ; extra == "all"
Requires-Dist: apache-airflow-providers-sftp ; extra == "all"
Requires-Dist: apache-airflow-providers-amazon>=5.0.0 ; extra == "amazon"
Requires-Dist: s3fs ; extra == "amazon"
Requires-Dist: smart-open[s3]>=5.2.1 ; extra == "amazon"
Requires-Dist: myst-parser>=0.17 ; extra == "doc"
Requires-Dist: sphinx>=4.4.0 ; extra == "doc"
Requires-Dist: sphinx-autoapi>=2.0.0 ; extra == "doc"
Requires-Dist: sphinx-rtd-theme ; extra == "doc"
Requires-Dist: airflow-provider-fivetran>=1.1.3 ; extra == "fivetran"
Requires-Dist: protobuf<=3.20 ; extra == "google"
Requires-Dist: apache-airflow-providers-google>=6.4.0 ; extra == "google"
Requires-Dist: sqlalchemy-bigquery>=1.3.0 ; extra == "google"
Requires-Dist: smart-open[gcs]>=5.2.1 ; extra == "google"
Requires-Dist: openlineage-airflow>=0.17.0 ; extra == "openlineage"
Requires-Dist: apache-airflow-providers-sftp ; extra == "sftp"
Requires-Dist: smart-open[ssh]>=5.2.1 ; extra == "sftp"
Requires-Dist: apache-airflow-providers-snowflake ; extra == "snowflake"
Requires-Dist: snowflake-sqlalchemy>=1.2.0 ; extra == "snowflake"
Requires-Dist: snowflake-connector-python[pandas]<3.0.0 ; extra == "snowflake"
Requires-Dist: pytest>=6.0 ; extra == "tests"
Requires-Dist: pytest-split ; extra == "tests"
Requires-Dist: pytest-dotenv ; extra == "tests"
Requires-Dist: requests-mock ; extra == "tests"
Requires-Dist: pytest-cov ; extra == "tests"
Requires-Dist: pytest-describe ; extra == "tests"
Requires-Dist: types-requests ; extra == "tests"
Requires-Dist: mypy ; extra == "tests"
Requires-Dist: sqlalchemy-stubs ; extra == "tests"
Project-URL: Home, https://astronomer.io/
Project-URL: Source, https://github.com/astronomer/astro-sdk/universal_transfer_operator
Provides-Extra: all
Provides-Extra: amazon
Provides-Extra: doc
Provides-Extra: fivetran
Provides-Extra: google
Provides-Extra: openlineage
Provides-Extra: sftp
Provides-Extra: snowflake
Provides-Extra: tests
